pydantic_ai_utils/__init__.py
pydantic_ai_utils/costs.py
pydantic_ai_utils/tools.py
pydantic_ai_utils-0.0.0.dist-info/METADATA
pydantic_ai_utils-0.0.0.dist-info/WHEEL
pydantic_ai_utils-0.0.0.dist-info/RECORD
