Metadata-Version: 2.4
Name: pydantic-ai-utils
Version: 0.0.0
Summary: A collection of utilities for Pydantic AI! 🚀
Requires-Python: >=3.9
Requires-Dist: google-search-results>=2.4.2
Requires-Dist: pydantic-ai>=0.0.46
